{
  "$schema": "https://developer.microsoft.com/json-schemas/fabric/item/report/definition/visualContainer/2.3.0/schema.json",
  "name": "e601f665c1c431cc9f2d",
  "position": {
    "x": 998.93284461316932,
    "y": 637.000654535934,
    "z": 32000,
    "height": 427.07998429113758,
    "width": 908.44979709386041,
    "tabOrder": 29000
  },
  "visual": {
    "visualType": "pivotTable",
    "query": {
      "queryState": {
        "Rows": {
          "projections": [
            {
              "field": {
                "Column": {
                  "Expression": {
                    "SourceRef": {
                      "Entity": "Subzone"
                    }
                  },
                  "Property": "sub_zone"
                }
              },
              "queryRef": "Subzone.sub_zone",
              "nativeQueryRef": "sub_zone",
              "active": true
            }
          ]
        },
        "Values": {
          "projections": [
            {
              "field": {
                "Measure": {
                  "Expression": {
                    "SourceRef": {
                      "Entity": "Key Measures"
                    }
                  },
                  "Property": "NS $"
                }
              },
              "queryRef": "Key Measures.NS $",
              "nativeQueryRef": "NS $"
            },
            {
              "field": {
                "Measure": {
                  "Expression": {
                    "SourceRef": {
                      "Entity": "Key Measures"
                    }
                  },
                  "Property": "RC %"
                }
              },
              "queryRef": "Key Measures.RC %",
              "nativeQueryRef": "RC %"
            },
            {
              "field": {
                "Measure": {
                  "Expression": {
                    "SourceRef": {
                      "Entity": "Key Measures"
                    }
                  },
                  "Property": "GM %"
                }
              },
              "queryRef": "Key Measures.GM %",
              "nativeQueryRef": "GM %"
            },
            {
              "field": {
                "Measure": {
                  "Expression": {
                    "SourceRef": {
                      "Entity": "Key Measures"
                    }
                  },
                  "Property": "Net Profit %"
                }
              },
              "queryRef": "Key Measures.Net Profit %",
              "nativeQueryRef": "NP %",
              "displayName": "NP %"
            },
            {
              "field": {
                "Measure": {
                  "Expression": {
                    "SourceRef": {
                      "Entity": "Key Measures"
                    }
                  },
                  "Property": "Net Error %"
                }
              },
              "queryRef": "Key Measures.Net Error %",
              "nativeQueryRef": "NE%",
              "displayName": "NE%"
            },
            {
              "field": {
                "Measure": {
                  "Expression": {
                    "SourceRef": {
                      "Entity": "Key Measures"
                    }
                  },
                  "Property": "Risk"
                }
              },
              "queryRef": "Key Measures.Risk",
              "nativeQueryRef": "Risk"
            },
            {
              "field": {
                "Measure": {
                  "Expression": {
                    "SourceRef": {
                      "Entity": "Key Measures"
                    }
                  },
                  "Property": "Atliq MS %"
                }
              },
              "queryRef": "Key Measures.Atliq MS %",
              "nativeQueryRef": "Atliq MS %"
            }
          ]
        }
      },
      "sortDefinition": {
        "sort": [
          {
            "field": {
              "Measure": {
                "Expression": {
                  "SourceRef": {
                    "Entity": "Key Measures"
                  }
                },
                "Property": "Atliq MS %"
              }
            },
            "direction": "Ascending"
          }
        ]
      }
    },
    "objects": {
      "grid": [
        {
          "properties": {
            "imageHeight": {
              "expr": {
                "Literal": {
                  "Value": "84D"
                }
              }
            },
            "rowPadding": {
              "expr": {
                "Literal": {
                  "Value": "1D"
                }
              }
            },
            "gridHorizontalWeight": {
              "expr": {
                "Literal": {
                  "Value": "3D"
                }
              }
            },
            "gridHorizontal": {
              "expr": {
                "Literal": {
                  "Value": "false"
                }
              }
            }
          }
        }
      ],
      "columnWidth": [
        {
          "properties": {},
          "selector": {
            "data": [
              {
                "scopeId": {
                  "Comparison": {
                    "ComparisonKind": 0,
                    "Left": {
                      "Column": {
                        "Expression": {
                          "SourceRef": {
                            "Entity": "P&L Columns"
                          }
                        },
                        "Property": "Column Header"
                      }
                    },
                    "Right": {
                      "Literal": {
                        "Value": "'2021'"
                      }
                    }
                  }
                }
              }
            ]
          }
        },
        {
          "properties": {},
          "selector": {
            "data": [
              {
                "scopeId": {
                  "Comparison": {
                    "ComparisonKind": 0,
                    "Left": {
                      "Column": {
                        "Expression": {
                          "SourceRef": {
                            "Entity": "P&L Columns"
                          }
                        },
                        "Property": "Column Header"
                      }
                    },
                    "Right": {
                      "Literal": {
                        "Value": "'LY'"
                      }
                    }
                  }
                }
              }
            ]
          }
        },
        {
          "properties": {},
          "selector": {
            "data": [
              {
                "scopeId": {
                  "Comparison": {
                    "ComparisonKind": 0,
                    "Left": {
                      "Column": {
                        "Expression": {
                          "SourceRef": {
                            "Entity": "P&L Columns"
                          }
                        },
                        "Property": "Column Header"
                      }
                    },
                    "Right": {
                      "Literal": {
                        "Value": "'YOY CHG'"
                      }
                    }
                  }
                }
              }
            ]
          }
        },
        {
          "properties": {
            "value": {
              "expr": {
                "Literal": {
                  "Value": "78.17936903656295D"
                }
              }
            }
          },
          "selector": {
            "data": [
              {
                "scopeId": {
                  "Comparison": {
                    "ComparisonKind": 0,
                    "Left": {
                      "Column": {
                        "Expression": {
                          "SourceRef": {
                            "Entity": "P&L Columns"
                          }
                        },
                        "Property": "Column Header"
                      }
                    },
                    "Right": {
                      "Literal": {
                        "Value": "'YOYCHG%'"
                      }
                    }
                  }
                }
              }
            ]
          }
        },
        {
          "properties": {
            "value": {
              "expr": {
                "Literal": {
                  "Value": "77.68680602474424D"
                }
              }
            }
          },
          "selector": {
            "data": [
              {
                "scopeId": {
                  "Comparison": {
                    "ComparisonKind": 0,
                    "Left": {
                      "Column": {
                        "Expression": {
                          "SourceRef": {
                            "Entity": "P&L Columns"
                          }
                        },
                        "Property": "Column Header"
                      }
                    },
                    "Right": {
                      "Literal": {
                        "Value": "'2022 EST'"
                      }
                    }
                  }
                }
              }
            ]
          }
        },
        {
          "properties": {
            "value": {
              "expr": {
                "Literal": {
                  "Value": "105.33984242248232D"
                }
              }
            }
          },
          "selector": {
            "metadata": "Key Measures.Net Profit %"
          }
        },
        {
          "properties": {
            "value": {
              "expr": {
                "Literal": {
                  "Value": "105.11657242943018D"
                }
              }
            }
          },
          "selector": {
            "metadata": "Key Measures.Net Error %"
          }
        },
        {
          "properties": {
            "value": {
              "expr": {
                "Literal": {
                  "Value": "110.06612806237983D"
                }
              }
            }
          },
          "selector": {
            "metadata": "Subzone.sub_zone"
          }
        },
        {
          "properties": {
            "value": {
              "expr": {
                "Literal": {
                  "Value": "191.66155701675078D"
                }
              }
            }
          },
          "selector": {
            "metadata": "Key Measures.Atliq MS %"
          }
        },
        {
          "properties": {
            "value": {
              "expr": {
                "Literal": {
                  "Value": "103.33837243539948D"
                }
              }
            }
          },
          "selector": {
            "metadata": "Key Measures.NS $"
          }
        },
        {
          "properties": {
            "value": {
              "expr": {
                "Literal": {
                  "Value": "89.22122535536693D"
                }
              }
            }
          },
          "selector": {
            "metadata": "Key Measures.RC %"
          }
        },
        {
          "properties": {
            "value": {
              "expr": {
                "Literal": {
                  "Value": "80.24811579297823D"
                }
              }
            }
          },
          "selector": {
            "metadata": "Key Measures.Risk"
          }
        },
        {
          "properties": {
            "value": {
              "expr": {
                "Literal": {
                  "Value": "113.03137343334018D"
                }
              }
            }
          },
          "selector": {
            "metadata": "Key Measures.GM %"
          }
        }
      ],
      "general": [
        {
          "properties": {}
        }
      ],
      "columnHeaders": [
        {
          "properties": {
            "fontSize": {
              "expr": {
                "Literal": {
                  "Value": "12D"
                }
              }
            },
            "fontFamily": {
              "expr": {
                "Literal": {
                  "Value": "'''Arial Black'''"
                }
              }
            },
            "fontColor": {
              "solid": {
                "color": {
                  "expr": {
                    "ThemeDataColor": {
                      "ColorId": 1,
                      "Percent": 0
                    }
                  }
                }
              }
            },
            "wordWrap": {
              "expr": {
                "Literal": {
                  "Value": "false"
                }
              }
            },
            "alignment": {
              "expr": {
                "Literal": {
                  "Value": "'Center'"
                }
              }
            },
            "titleAlignment": {
              "expr": {
                "Literal": {
                  "Value": "'Left'"
                }
              }
            }
          }
        }
      ],
      "columnFormatting": [
        {
          "properties": {
            "labelPrecision": {
              "expr": {
                "Literal": {
                  "Value": "1L"
                }
              }
            },
            "labelDisplayUnits": {
              "expr": {
                "Literal": {
                  "Value": "1000000D"
                }
              }
            }
          },
          "selector": {
            "metadata": "Key Measures.NS $"
          }
        },
        {
          "properties": {
            "labelPrecision": {
              "expr": {
                "Literal": {
                  "Value": "1L"
                }
              }
            }
          },
          "selector": {
            "metadata": "Key Measures.RC %"
          }
        },
        {
          "properties": {
            "labelPrecision": {
              "expr": {
                "Literal": {
                  "Value": "1L"
                }
              }
            }
          },
          "selector": {
            "metadata": "Key Measures.GM %"
          }
        },
        {
          "properties": {
            "labelPrecision": {
              "expr": {
                "Literal": {
                  "Value": "1L"
                }
              }
            }
          },
          "selector": {
            "metadata": "Key Measures.Net Profit %"
          }
        },
        {
          "properties": {
            "labelPrecision": {
              "expr": {
                "Literal": {
                  "Value": "1L"
                }
              }
            }
          },
          "selector": {
            "metadata": "Key Measures.Net Error %"
          }
        },
        {
          "properties": {
            "dataBars": {
              "positiveColor": {
                "solid": {
                  "color": {
                    "expr": {
                      "Literal": {
                        "Value": "'#44A598'"
                      }
                    }
                  }
                }
              },
              "negativeColor": {
                "solid": {
                  "color": {
                    "expr": {
                      "Literal": {
                        "Value": "'minColor'"
                      }
                    }
                  }
                }
              },
              "axisColor": {
                "solid": {
                  "color": {
                    "expr": {
                      "Literal": {
                        "Value": "'#FFFFFF'"
                      }
                    }
                  }
                }
              },
              "reverseDirection": {
                "expr": {
                  "Literal": {
                    "Value": "false"
                  }
                }
              },
              "hideText": {
                "expr": {
                  "Literal": {
                    "Value": "false"
                  }
                }
              },
              "totalMatchingOption": {
                "expr": {
                  "Literal": {
                    "Value": "1L"
                  }
                }
              }
            }
          },
          "selector": {
            "metadata": "Key Measures.Atliq MS %"
          }
        }
      ],
      "values": [
        {
          "properties": {
            "icon": {
              "kind": "Icon",
              "layout": {
                "expr": {
                  "Literal": {
                    "Value": "'After'"
                  }
                }
              },
              "verticalAlignment": {
                "expr": {
                  "Literal": {
                    "Value": "'Top'"
                  }
                }
              },
              "value": {
                "expr": {
                  "Conditional": {
                    "Cases": [
                      {
                        "Condition": {
                          "Comparison": {
                            "ComparisonKind": 0,
                            "Left": {
                              "Measure": {
                                "Expression": {
                                  "SourceRef": {
                                    "Entity": "Key Measures"
                                  }
                                },
                                "Property": "GM % Variance"
                              }
                            },
                            "Right": {
                              "Literal": {
                                "Value": "0D"
                              }
                            }
                          }
                        },
                        "Value": {
                          "Literal": {
                            "Value": "'CircleMedium'"
                          }
                        }
                      },
                      {
                        "Condition": {
                          "And": {
                            "Left": {
                              "Comparison": {
                                "ComparisonKind": 2,
                                "Left": {
                                  "Measure": {
                                    "Expression": {
                                      "SourceRef": {
                                        "Entity": "Key Measures"
                                      }
                                    },
                                    "Property": "GM % Variance"
                                  }
                                },
                                "Right": {
                                  "Literal": {
                                    "Value": "-1D"
                                  }
                                }
                              }
                            },
                            "Right": {
                              "Comparison": {
                                "ComparisonKind": 3,
                                "Left": {
                                  "Measure": {
                                    "Expression": {
                                      "SourceRef": {
                                        "Entity": "Key Measures"
                                      }
                                    },
                                    "Property": "GM % Variance"
                                  }
                                },
                                "Right": {
                                  "Literal": {
                                    "Value": "0D"
                                  }
                                }
                              }
                            }
                          }
                        },
                        "Value": {
                          "Literal": {
                            "Value": "'ColoredArrowUp'"
                          }
                        }
                      },
                      {
                        "Condition": {
                          "And": {
                            "Left": {
                              "Comparison": {
                                "ComparisonKind": 2,
                                "Left": {
                                  "Measure": {
                                    "Expression": {
                                      "SourceRef": {
                                        "Entity": "Key Measures"
                                      }
                                    },
                                    "Property": "GM % Variance"
                                  }
                                },
                                "Right": {
                                  "Literal": {
                                    "Value": "0D"
                                  }
                                }
                              }
                            },
                            "Right": {
                              "Comparison": {
                                "ComparisonKind": 3,
                                "Left": {
                                  "Measure": {
                                    "Expression": {
                                      "SourceRef": {
                                        "Entity": "Key Measures"
                                      }
                                    },
                                    "Property": "GM % Variance"
                                  }
                                },
                                "Right": {
                                  "Literal": {
                                    "Value": "1D"
                                  }
                                }
                              }
                            }
                          }
                        },
                        "Value": {
                          "Literal": {
                            "Value": "'ColoredArrowDown'"
                          }
                        }
                      }
                    ]
                  }
                }
              }
            }
          },
          "selector": {
            "data": [
              {
                "dataViewWildcard": {
                  "matchingOption": 1
                }
              }
            ],
            "metadata": "Key Measures.GM %"
          }
        },
        {
          "properties": {
            "icon": {
              "kind": "Icon",
              "layout": {
                "expr": {
                  "Literal": {
                    "Value": "'After'"
                  }
                }
              },
              "verticalAlignment": {
                "expr": {
                  "Literal": {
                    "Value": "'Top'"
                  }
                }
              },
              "value": {
                "expr": {
                  "Conditional": {
                    "Cases": [
                      {
                        "Condition": {
                          "Comparison": {
                            "ComparisonKind": 0,
                            "Left": {
                              "Measure": {
                                "Expression": {
                                  "SourceRef": {
                                    "Entity": "Key Measures"
                                  }
                                },
                                "Property": "DELTA NP %"
                              }
                            },
                            "Right": {
                              "Literal": {
                                "Value": "0D"
                              }
                            }
                          }
                        },
                        "Value": {
                          "Literal": {
                            "Value": "'CircleMedium'"
                          }
                        }
                      },
                      {
                        "Condition": {
                          "And": {
                            "Left": {
                              "Comparison": {
                                "ComparisonKind": 2,
                                "Left": {
                                  "Measure": {
                                    "Expression": {
                                      "SourceRef": {
                                        "Entity": "Key Measures"
                                      }
                                    },
                                    "Property": "DELTA NP %"
                                  }
                                },
                                "Right": {
                                  "Literal": {
                                    "Value": "-1D"
                                  }
                                }
                              }
                            },
                            "Right": {
                              "Comparison": {
                                "ComparisonKind": 3,
                                "Left": {
                                  "Measure": {
                                    "Expression": {
                                      "SourceRef": {
                                        "Entity": "Key Measures"
                                      }
                                    },
                                    "Property": "DELTA NP %"
                                  }
                                },
                                "Right": {
                                  "Literal": {
                                    "Value": "0D"
                                  }
                                }
                              }
                            }
                          }
                        },
                        "Value": {
                          "Literal": {
                            "Value": "'ColoredArrowDown'"
                          }
                        }
                      },
                      {
                        "Condition": {
                          "And": {
                            "Left": {
                              "Comparison": {
                                "ComparisonKind": 2,
                                "Left": {
                                  "Measure": {
                                    "Expression": {
                                      "SourceRef": {
                                        "Entity": "Key Measures"
                                      }
                                    },
                                    "Property": "DELTA NP %"
                                  }
                                },
                                "Right": {
                                  "Literal": {
                                    "Value": "0D"
                                  }
                                }
                              }
                            },
                            "Right": {
                              "Comparison": {
                                "ComparisonKind": 3,
                                "Left": {
                                  "Measure": {
                                    "Expression": {
                                      "SourceRef": {
                                        "Entity": "Key Measures"
                                      }
                                    },
                                    "Property": "DELTA NP %"
                                  }
                                },
                                "Right": {
                                  "Literal": {
                                    "Value": "1D"
                                  }
                                }
                              }
                            }
                          }
                        },
                        "Value": {
                          "Literal": {
                            "Value": "'ColoredArrowUp'"
                          }
                        }
                      }
                    ]
                  }
                }
              }
            }
          },
          "selector": {
            "data": [
              {
                "dataViewWildcard": {
                  "matchingOption": 1
                }
              }
            ],
            "metadata": "Key Measures.Net Profit %"
          }
        },
        {
          "properties": {
            "fontSize": {
              "expr": {
                "Literal": {
                  "Value": "10D"
                }
              }
            },
            "fontFamily": {
              "expr": {
                "Literal": {
                  "Value": "'''Arial Black'''"
                }
              }
            },
            "bold": {
              "expr": {
                "Literal": {
                  "Value": "true"
                }
              }
            }
          }
        }
      ],
      "blankRows": [
        {
          "properties": {
            "showBlankRows": {
              "expr": {
                "Literal": {
                  "Value": "true"
                }
              }
            }
          }
        }
      ],
      "rowHeaders": [
        {
          "properties": {
            "fontFamily": {
              "expr": {
                "Literal": {
                  "Value": "'''Arial Black'''"
                }
              }
            },
            "fontColor": {
              "solid": {
                "color": {
                  "expr": {
                    "ThemeDataColor": {
                      "ColorId": 1,
                      "Percent": 0
                    }
                  }
                }
              }
            },
            "fontSize": {
              "expr": {
                "Literal": {
                  "Value": "12D"
                }
              }
            },
            "steppedLayoutIndentation": {
              "expr": {
                "Literal": {
                  "Value": "4D"
                }
              }
            }
          }
        }
      ]
    },
    "visualContainerObjects": {
      "padding": [
        {
          "properties": {
            "top": {
              "expr": {
                "Literal": {
                  "Value": "1D"
                }
              }
            },
            "bottom": {
              "expr": {
                "Literal": {
                  "Value": "1D"
                }
              }
            },
            "left": {
              "expr": {
                "Literal": {
                  "Value": "1D"
                }
              }
            },
            "right": {
              "expr": {
                "Literal": {
                  "Value": "1D"
                }
              }
            }
          }
        }
      ],
      "lockAspect": [
        {
          "properties": {
            "show": {
              "expr": {
                "Literal": {
                  "Value": "true"
                }
              }
            }
          }
        }
      ],
      "general": [
        {
          "properties": {
            "keepLayerOrder": {
              "expr": {
                "Literal": {
                  "Value": "false"
                }
              }
            }
          }
        }
      ],
      "title": [
        {
          "properties": {
            "show": {
              "expr": {
                "Literal": {
                  "Value": "false"
                }
              }
            },
            "titleWrap": {
              "expr": {
                "Literal": {
                  "Value": "true"
                }
              }
            }
          }
        }
      ],
      "stylePreset": [
        {
          "properties": {
            "name": {
              "expr": {
                "Literal": {
                  "Value": "'None'"
                }
              }
            }
          }
        }
      ],
      "background": [
        {
          "properties": {
            "show": {
              "expr": {
                "Literal": {
                  "Value": "true"
                }
              }
            },
            "transparency": {
              "expr": {
                "Literal": {
                  "Value": "29D"
                }
              }
            }
          }
        }
      ],
      "dropShadow": [
        {
          "properties": {
            "show": {
              "expr": {
                "Literal": {
                  "Value": "false"
                }
              }
            }
          }
        }
      ],
      "border": [
        {
          "properties": {
            "width": {
              "expr": {
                "Literal": {
                  "Value": "1D"
                }
              }
            }
          }
        }
      ]
    },
    "drillFilterOtherVisuals": true
  }
}