{
  "$schema": "https://developer.microsoft.com/json-schemas/fabric/item/report/definition/visualContainer/2.3.0/schema.json",
  "name": "848996a4599eca3a9d66",
  "position": {
    "x": 1329.509433962264,
    "y": 539.7735849056603,
    "z": 19000,
    "height": 99.622641509433961,
    "width": 99.622641509433961,
    "tabOrder": 18000
  },
  "visual": {
    "visualType": "image",
    "objects": {
      "general": [
        {
          "properties": {
            "imageUrl": {
              "expr": {
                "ResourcePackageItem": {
                  "PackageName": "RegisteredResources",
                  "PackageType": 1,
                  "ItemName": "Phoenix_10_A_minimalist_modern29186073762336895.jpg"
                }
              }
            }
          }
        }
      ]
    },
    "visualContainerObjects": {
      "visualLink": [
        {
          "properties": {
            "show": {
              "expr": {
                "Literal": {
                  "Value": "true"
                }
              }
            },
            "type": {
              "expr": {
                "Literal": {
                  "Value": "'PageNavigation'"
                }
              }
            },
            "navigationSection": {
              "expr": {
                "Literal": {
                  "Value": "'bc60904141e628d6a025'"
                }
              }
            }
          }
        }
      ]
    },
    "drillFilterOtherVisuals": true
  },
  "howCreated": "InsertVisualButton"
}