{
  "$schema": "https://developer.microsoft.com/json-schemas/fabric/item/report/definition/visualContainer/2.3.0/schema.json",
  "name": "257cfe51dc77c67ae991",
  "position": {
    "x": 800.60377358490564,
    "y": 34.415094339622641,
    "z": 15000,
    "height": 41.660377358490564,
    "width": 110.49056603773585,
    "tabOrder": 16000
  },
  "visual": {
    "visualType": "textbox",
    "objects": {
      "general": [
        {
          "properties": {
            "paragraphs": [
              {
                "textRuns": [
                  {
                    "value": "MARKETING",
                    "textStyle": {
                      "fontWeight": "bold",
                      "fontFamily": "Arial Black"
                    }
                  }
                ]
              }
            ]
          }
        }
      ]
    },
    "visualContainerObjects": {
      "background": [
        {
          "properties": {
            "show": {
              "expr": {
                "Literal": {
                  "Value": "false"
                }
              }
            }
          }
        }
      ]
    },
    "drillFilterOtherVisuals": true
  }
}